pyopenuv/__init__.py
pyopenuv/client.py
pyopenuv/const.py
pyopenuv/errors.py
pyopenuv/py.typed
pyopenuv-2023.12.0.dist-info/LICENSE
pyopenuv-2023.12.0.dist-info/METADATA
pyopenuv-2023.12.0.dist-info/WHEEL
pyopenuv-2023.12.0.dist-info/RECORD
